[
    {
        "oNo": 890982931,
        "Organ": "永豐餘生技股份有限公司",
        "eNo": 91300280,
        "Position": "行銷專員(型錄&amp;商品企劃)",
        "Matter": "1. 每季型錄單元企劃、編輯、及時程追蹤\n2. 門市POSM規劃\n3. 動態影音食譜企劃\n4. 整合公司內部需求與外部廠商溝通\n5. 網紅及名人企劃洽談與執行\n6. 商品料號管理建置\n7. 行銷數據分析整理",
        "WorkCity": "台北市中正區",
        "WorkCity_i": 100101,
        "Salary": "月薪 40,000元 以上",
        "DutyArr": [
            {
                "DutyNo": 130103,
                "DutyName": "行銷企劃人員"
            },
            {
                "DutyNo": 130106,
                "DutyName": "產品企劃人員"
            },
            {
                "DutyNo": 130202,
                "DutyName": "活動企劃人員"
            }
        ],
        "FeatureArr": [],
        "Experience": "經驗不拘",
        "Grade": "大學、碩士、博士",
        "dateChange": "2020/02/10 11:18:41",
        "RowNo": 1
    },
    {
        "oNo": 890982931,
        "Organ": "永豐餘生技股份有限公司",
        "eNo": 91238177,
        "Position": "西餐主廚/副主廚 (上海_GREEN&amp;SAFE餐廳)",
        "Matter": "1.負責營運廚務生產與管理,餐點料理及品質維護\n2.執行門市廚務人員教育訓練, 遵守SOP精神並且嚴格執行\n3.謹守食材衛生管理條例之規範且善於成本分析與食材控制運用\n4.對於餐飲市場趨勢有敏銳的觀察和解析力\n5.協助完成中央廚房菜式研發與上市推廣",
        "WorkCity": "上海市",
        "WorkCity_i": 110300,
        "Salary": "面議（經常性薪資4萬/月含以上）",
        "DutyArr": [
            {
                "DutyNo": 270204,
                "DutyName": "西式廚師"
            }
        ],
        "FeatureArr": [],
        "Experience": "10年以上工作經驗",
        "Grade": "學歷不拘",
        "dateChange": "2020/02/08 01:10:06",
        "RowNo": 2
    },
    {
        "oNo": 890982931,
        "Organ": "永豐餘生技股份有限公司",
        "eNo": 91238167,
        "Position": "中餐主廚/副主廚 (上海_齊民市集火鍋餐廳)",
        "Matter": "1.負責營運廚務生產與管理,餐點料理及品質維護\n2.執行門市廚務人員教育訓練, 遵守SOP精神並且嚴格執行\n3.謹守食材衛生管理條例之規範且善於成本分析與食材控制運用\n4.對於餐飲市場趨勢有敏銳的觀察和解析力\n5.協助完成中央廚房菜式研發與上市推廣",
        "WorkCity": "上海市",
        "WorkCity_i": 110300,
        "Salary": "面議（經常性薪資4萬/月含以上）",
        "DutyArr": [
            {
                "DutyNo": 270204,
                "DutyName": "西式廚師"
            }
        ],
        "FeatureArr": [],
        "Experience": "10年以上工作經驗",
        "Grade": "學歷不拘",
        "dateChange": "2020/02/08 01:10:06",
        "RowNo": 3
    },
    {
        "oNo": 890982931,
        "Organ": "永豐餘生技股份有限公司",
        "eNo": 91219016,
        "Position": "行銷專員 (官網&amp;電子商務)",
        "Matter": "1. 專案: 新官網及APP，掌管開發時程\n 整合公司內部需求與外部廠商溝通\n 規劃前後台功能及整體流程動線\n2. 負責官網之營運\n 官網前台及後台管理及問題解決，與外部廠商溝通\n 商品上下架、庫存追蹤及管理\n 網頁內容更新及增減活動頁面\n EC行銷活動執行，業績目標達成、成效追蹤\n3. 網路行銷活動執行，成效追蹤及分析評估\n4. 分析網站指標數據，制定改善策",
        "WorkCity": "台北市中正區",
        "WorkCity_i": 100101,
        "Salary": "面議（經常性薪資4萬/月含以上）",
        "DutyArr": [
            {
                "DutyNo": 130106,
                "DutyName": "產品企劃人員"
            },
            {
                "DutyNo": 130103,
                "DutyName": "行銷企劃人員"
            }
        ],
        "FeatureArr": [],
        "Experience": "4年以上工作經驗",
        "Grade": "專科、大學、碩士",
        "dateChange": "2020/02/08 01:10:06",
        "RowNo": 4
    },
    {
        "oNo": 890982931,
        "Organ": "永豐餘生技股份有限公司",
        "eNo": 91212136,
        "Position": "行銷專員 (GREEN&amp;SAFE零售_上海)",
        "Matter": "1. GREEN & SAFE 商品市場調查分析，熟悉產業競爭及市場情報蒐集、彙整，定期報告分析銷售進度及市場佔有率。\n2. 協助GREEN & SAFE 零售銷售分析與問題點發覺改善建議，成本及損益推估\n3. GREEN & SAFE 零售商品概念開發 / 產品上下架\n4. 經管會/產銷協調、成本價格管理\n5. 熟悉品牌形象，協助品牌形象經營，門市銷售規劃與執行\n6. 熟悉廣宣、公關、行銷活動企劃與執行\n7. 異業合作統整及管理\n8. 展店策畫及執行\n9. 協調與解決跨部門之工作\n10.其他主管交辦事項",
        "WorkCity": "上海市",
        "WorkCity_i": 110300,
        "Salary": "面議（經常性薪資4萬/月含以上）",
        "DutyArr": [
            {
                "DutyNo": 130103,
                "DutyName": "行銷企劃人員"
            },
            {
                "DutyNo": 130202,
                "DutyName": "活動企劃人員"
            },
            {
                "DutyNo": 130106,
                "DutyName": "產品企劃人員"
            }
        ],
        "FeatureArr": [],
        "Experience": "6年以上工作經驗",
        "Grade": "大學、碩士、博士",
        "dateChange": "2020/02/08 01:10:06",
        "RowNo": 5
    },
    {
        "oNo": 890982931,
        "Organ": "永豐餘生技股份有限公司",
        "eNo": 91204721,
        "Position": "外場領檯 (山海樓手工台菜餐廳)",
        "Matter": "■■■■■■■■■■ 薪資．休假規範 ■■■■■■■■■■\n正職每天排班8小時，月排休9天以上\n月薪30000-34000元以上+每月業績獎金\n完善的教育訓練制度。\n\n■■■■■■■■■■ 山海樓 ■■■■■■■■■■\n2019米其林一星餐廳，山海樓2014年從中山北路二段開始，2018年搬遷至台北市仁愛路二段上，秉持找尋與傳承台菜料理的精神，以台灣原生品種食材，復刻出記憶中的經典老台菜味道，也創作出當代的台灣精緻菜餚，山海樓特有的食材室隨著季節陳列不同的季節蔬菜及野生魚貨，每天從自家有機農場及漁港直送，讓客人可以知道真正當令的味道。\n\n山海樓以說菜的方式傳遞每道台菜背後蘊含的意義及文化，讓每一位客人不只享受台菜香，更品嘗到每一道台菜文化，山海樓歡迎每一位重視台菜文化、中式料理的您加入！\n\n1.帶領客人至座位並遞上菜單及知會當區領班\n2.負責接聽餐廳電話及線上下訂位安排相關作業\n3.會計作業(包含客人結帳,打烊之帳務核對)\n4.執行總公司會計部門之聯繫與核對帳務\n5.適時支援各項事務",
        "WorkCity": "台北市中正區",
        "WorkCity_i": 100101,
        "Salary": "月薪 30,000元 至 34,000元",
        "DutyArr": [
            {
                "DutyNo": 270213,
                "DutyName": "餐飲服務人員"
            },
            {
                "DutyNo": 270305,
                "DutyName": "飯店／旅館櫃檯人員"
            },
            {
                "DutyNo": 270306,
                "DutyName": "飯店／旅館服務人員"
            }
        ],
        "FeatureArr": [],
        "Experience": "5年以上工作經驗",
        "Grade": "高中職、專科、大學",
        "dateChange": "2020/02/08 01:10:06",
        "RowNo": 6
    },
    {
        "oNo": 890982931,
        "Organ": "永豐餘生技股份有限公司",
        "eNo": 91175963,
        "Position": "內場正職服務員(齊民火鍋_東門市集)",
        "Matter": "■■■■■■■■■■ 聯合面談．徵才 ■■■■■■■■■■\n我們歡迎有志於零售服務業發展，且對食物熱情、喜歡烹調，\n具服務熱忱的您，加入我們的團隊；\n於每周三下午15:00~17:00在總公司舉辦聯合面談，徵才；\n由營運主管和人力資源單位親自與您面談。\n\n歡迎每週三當天親臨總公司台北市重慶南路二段51號8樓，\n近捷運中正紀念堂2號出口。\n\n■■■■■■■■■■ 薪資．休假規範 ■■■■■■■■■■\n正職每天排班8小時，月排休9天以上，\n月薪(起薪)28000元+每月業績獎金，\n每月月考核，每季產品訓練，配合各門市排班、支援、輪調、升遷等。\n\n■■■■■■■■■■ 齊民東門市集 ■■■■■■■■■■\n「齊民市集」是隸屬於永豐餘生技旗下餐飲品牌，以生態美食為核心，自有農場堅持有機農法栽培，店內嚴選來自國內外全球的有機天然食材，並以公平交易取得，個人化的火鍋選擇，提供給大眾多樣安心的溫暖鍋物。\n1.負責洗、剝、削、切各種食材，以完成烹飪的前置工作。\n2.依照客人的點單，準備不同菜色所需要的食材。\n3.於出菜時負責菜餚擺盤或調整份量之工作。\n4.各工作站輪調學習。",
        "WorkCity": "台北市大安區",
        "WorkCity_i": 100105,
        "Salary": "月薪 28,000元 至 32,000元",
        "DutyArr": [
            {
                "DutyNo": 270214,
                "DutyName": "餐廚助手"
            },
            {
                "DutyNo": 270203,
                "DutyName": "中式廚師"
            },
            {
                "DutyNo": 270208,
                "DutyName": "其他料理廚師"
            }
        ],
        "FeatureArr": [],
        "Experience": "1年以上工作經驗",
        "Grade": "高中職、專科、大學、碩士、博士",
        "dateChange": "2020/02/08 01:10:06",
        "RowNo": 7
    },
    {
        "oNo": 890982931,
        "Organ": "永豐餘生技股份有限公司",
        "eNo": 91160372,
        "Position": "約聘銷售行政人員(和田生活)",
        "Matter": "■■■■■■■■■■關於和田 生活 ■■■■■■■■■■\n1998年，永豐餘生技從宜蘭一片好山好水的沃土農場出發，\n依據季節生產多樣性的有機物產，豐富每個人家中的餐桌。\n2016年，和田生活將「從農田到餐桌」的品牌概念延伸到生活住宅，\n重新思考住宅的定義，打造自然與生活互相平衡的生態烏托邦(Ecotopia)。\n旨在都市中打造「吃得好，住得好，又節能」的理想住宅，\n適合老中青三代互動式的Ecotopia。\n\n公司網址：www.ecotopialife.com\n\n產業描述：建設事業、土地開發、房屋銷售、建築與室內設計\n\n\n1. 處理房屋銷售現場專案事務\n2. 負責市調及會議相關事務\n3. 負責銷售現場文書作業、報表製作、銷售及服務事宜\n4. 督導廠商及媒體項目執行\n5. 其他主管交辦事項",
        "WorkCity": "台北市中正區",
        "WorkCity_i": 100101,
        "Salary": "面議（經常性薪資4萬/月含以上）",
        "DutyArr": [
            {
                "DutyNo": 100302,
                "DutyName": "行政人員"
            },
            {
                "DutyNo": 100304,
                "DutyName": "行政助理"
            },
            {
                "DutyNo": 120212,
                "DutyName": "不動產經紀人／營業員"
            }
        ],
        "FeatureArr": [],
        "Experience": "經驗不拘",
        "Grade": "專科、大學、碩士、博士",
        "dateChange": "2020/02/08 01:10:06",
        "RowNo": 8
    },
    {
        "oNo": 890982931,
        "Organ": "永豐餘生技股份有限公司",
        "eNo": 86008135,
        "Position": "電話銷售主任/副理(客服部)",
        "Matter": "1. 領導客服部團隊，協助內外部溝通協調 \n2. 績效評核及制定獎勵福利制度 \n3. 管理與制定電銷作業流程、人力調配 \n4. 成本控管、損益分析與業績目標達成 \n5. 輔導管理與訓練人員電話接聽 \n6. 其他主管交辦事項",
        "WorkCity": "台北市中正區",
        "WorkCity_i": 100101,
        "Salary": "面議（經常性薪資4萬/月含以上）",
        "DutyArr": [
            {
                "DutyNo": 120305,
                "DutyName": "電話客服人員"
            },
            {
                "DutyNo": 120209,
                "DutyName": "電話行銷人員"
            },
            {
                "DutyNo": 130106,
                "DutyName": "產品企劃人員"
            }
        ],
        "FeatureArr": [],
        "Experience": "經驗不拘",
        "Grade": "專科以上畢業",
        "dateChange": "2020/02/08 01:10:06",
        "RowNo": 9
    },
    {
        "oNo": 890982931,
        "Organ": "永豐餘生技股份有限公司",
        "eNo": 85942991,
        "Position": "零售計時服務員(GREEN&amp;SAFE真食物專賣店_北新門市)",
        "Matter": "■■■■■■■■■■ 聯合面談．徵才 ■■■■■■■■■■ \n我們歡迎有志於零售服務業發展，且對食物熱情、喜歡烹調， \n具服務熱忱的您，加入我們的團隊； \n於每周三下午15:00~17:00在總公司舉辦聯合面談，徵才； \n由營運主管和人力資源單位親自與您面談。 \n\n歡迎每週三當天親臨總公司台北市重慶南路二段8樓， \n近捷運中正紀念堂站2號出口。 \n\n■■■■■■■■■■ 薪資．休假規範 ■■■■■■■■■■ \n正職每天排班8小時，月排休9天以上， \n月薪(起薪)28000元+每月業績獎金， \n完善的教育訓練制度，入職第二個月進行初階產品考試，對應調薪； \n每月月考核，每月產品訓練，配合各門市排班、支援、輪調、升遷等。 \n\n兼職早班/中班/晚班可任選，每月至少配合80小時； \n兼職假日班，每月至少配合45小時。 \n\n■■■■■■■■■■ 真食物專賣店 ■■■■■■■■■■ \n「GREEN&SAFE」是隸屬於永豐餘生技旗下餐飲品牌，以生態美食為核心，自有農場堅持有機農法栽培，店內嚴選來自國內外全球的有機天然食材，並以公平交易取得，經專業師傅研發烹調，提供消費者無論何時皆能悠閒的享受美味健康餐點。 \n\n同時提供100％無添加的各式冷凍省時達人料理，冷藏生鮮食材和乾貨雜糧，最自然甘甜的美味；消費者可依個人喜好選購回家烹調，店內同時有專業的服務人員提供產品的試吃及解說，提供給消費者回歸台灣傳統市場中，站在客人的角度設身處地著想的購物體驗。 \n\nGreen&Safe歡迎每一位對食材、料理有熱情的您加入！ \n\n1.商品銷售、服務客戶。 \n2.商品進貨、貼條碼、上架。 \n3.分貨處理。 \n4.商品退貨(瑕疪品)處理。 \n5.商品出售之相關細節(KEY帳、開發票)。 \n6.門市例行性清潔工作。 \n7.其他門市營運相關。",
        "WorkCity": "新北市新店區",
        "WorkCity_i": 100211,
        "Salary": "時薪 158元",
        "DutyArr": [
            {
                "DutyNo": 120403,
                "DutyName": "門市／店員／專櫃人員"
            }
        ],
        "FeatureArr": [],
        "Experience": "經驗不拘",
        "Grade": "學歷不拘",
        "dateChange": "2020/02/08 01:10:06",
        "RowNo": 10
    }
]